geotran/__init__.py
geotran/geofuncs.py
geotran/raster.py
rasteric/__init__.py
rasteric/os.py
rasteric/raster.py
rasteric-1.0.0.dist-info/LICENSE.txt
rasteric-1.0.0.dist-info/METADATA
rasteric-1.0.0.dist-info/WHEEL
rasteric-1.0.0.dist-info/top_level.txt
rasteric-1.0.0.dist-info/RECORD
