Metadata-Version: 2.1
Name: rasteric
Version: 1.0.0
Summary: A Comprehensive Geospatial Library
Home-page: https://github.com/tnmthai/rasteric
Author: Thai Tran
Author-email: me@tnmthai.com
License: MIT
Project-URL: Bug Tracker, https://github.com/tnmthai/rasteric/issues
Project-URL: repository, https://github.com/tnmthai/rasteric
Classifier: Programming Language :: Python :: 3
Classifier: License :: OSI Approved :: MIT License
Classifier: Operating System :: OS Independent
Requires-Python: >=3.6
License-File: LICENSE.txt
Requires-Dist: rasterio>=1.0
Requires-Dist: matplotlib>=3.0
Requires-Dist: shapely>=1.7
Requires-Dist: geopandas>=0.9
Requires-Dist: numpy>=1.18
Requires-Dist: pandas>=1.0
Requires-Dist: scikit-learn>=0.24
Requires-Dist: rasterstats
